qserious/__init__.py
qserious/qserious.py
qserious-0.2.10.dist-info/DESCRIPTION.rst
qserious-0.2.10.dist-info/LICENSE.txt
qserious-0.2.10.dist-info/METADATA
qserious-0.2.10.dist-info/RECORD
qserious-0.2.10.dist-info/WHEEL
qserious-0.2.10.dist-info/metadata.json
qserious-0.2.10.dist-info/top_level.txt
tests/__init__.py
tests/brackets-to-dots-test.py
tests/deserialize-test.py
tests/keys-to-brackets-test.py
tests/serialize-test.py
