Metadata-Version: 2.0
Name: qserious
Version: 0.2.10
Summary: query string serializer/deserializer
Home-page: https://github.com/pyKilt/qserious
Author: Jesus Germade
Author-email: jesus@germade.es
License: MIT
Keywords: querystring,query,string,serializer,deserializer,serialize,deserialize
Platform: UNKNOWN
